pystorcli/__init__.py
pystorcli/cachevault.py
pystorcli/common.py
pystorcli/controller.py
pystorcli/drive.py
pystorcli/enclosure.py
pystorcli/exc.py
pystorcli/virtualdrive.py
pystorcli-0.2.1.dist-info/METADATA
pystorcli-0.2.1.dist-info/RECORD
pystorcli-0.2.1.dist-info/WHEEL
pystorcli-0.2.1.dist-info/top_level.txt
