Metadata-Version: 2.1
Name: pystorcli
Version: 0.2.1
Summary: StorCLI module wrapper
Home-page: https://github.com/Chillisystems/pystorcli
Author: Martin Dojcak
Author-email: martin@dojcak.sk
License: UNKNOWN
Platform: UNKNOWN
Classifier: Programming Language :: Python :: 3
Classifier: Intended Audience :: Developers
Classifier: Intended Audience :: Information Technology
Classifier: Intended Audience :: System Administrators
Classifier: License :: OSI Approved :: GNU General Public License v3 or later (GPLv3+)
Classifier: Natural Language :: English
Classifier: Operating System :: POSIX
Classifier: Topic :: System :: Hardware :: Hardware Drivers
Classifier: Topic :: System :: Installation/Setup
Classifier: Topic :: Software Development :: Libraries :: Python Modules
Classifier: Programming Language :: Python
